[{"name":"Зарічанська","type":"вул.","houses":[[1,2,3,4,5,6,7,8,9,10,11,13,14,15,16,17,18,19,20,21,23,24,26,28,30,31,32,36,38]]},{"name":"Молодіжна","type":"вул.","houses":[[3,4,7,8,9,10,11,12,13,14,15,16,17,18,19,21,23,25,26,27,29,44,48]]},{"name":"Садова","type":"вул.","houses":[[2,3,4,5,6,7,9,"10\/1","10\/2","10\/3","10\/4",11,12,16,20,22,26,32,34,36,38,40]]},{"name":"Центральна","type":"вул.","houses":[[1,3,4,5,6,7,8,9,10,11,12,13,15,17,19,23,24,25,26,"26А",28,29,30,31,33,35,37,39,41,43,45]]},{"name":"Зарічанський","type":"пров.","houses":[[1,2,3]]},{"name":"Центральний","type":"пров.","houses":[[1,2,4,6]]}]