[{"name":"Залісна","type":"вул.","houses":[[1,2,3,4,5,6,7,8,9,10,11,12,13,14,15,16,17,18,19,20,21,22,23,24]]},{"name":"Зарічна","type":"вул.","houses":[[1,2,3,4,5,6,7,8,9,10,11,12,13,14]]},{"name":"І.Франка","type":"вул.","houses":[[1,2,3,4,5,6,7,8,9,10,11,12]]},{"name":"Котика","type":"вул.","houses":[[1,2,3,4,5,6,7,8,9,10,11,12,13,14,15,16,17,18,19,20,21,22,23,24,25,26]]},{"name":"Миколи Коцюбинського","type":"вул.","houses":[[1,2,3,4,5,6,7,8,9,10,11,12,13,14,15,16,17,18,19,20,21,22,23,24,25,26,27,28,29,30,31,32,33,34,35,36,37,38,39,40,41,42]]},{"name":"Миру","type":"вул.","houses":[[1,2,3,4,5,6,7,8,9,10,11,12,13,14,15,16,17,18,19,20]]},{"name":"Молодіжна","type":"вул.","houses":[[1,2,3,4,5,6,7,8,9,10,11,12,13,14,15,16,17,18,19]]},{"name":"Садова","type":"вул.","houses":[[1,2,3,4,5,6,7,8,9,10,11,12,13,14]]},{"name":"Сонячна","type":"вул.","houses":[[1,2,3,4,5,6,7,8,9,10,11,12,13,14,15,16,17,18]]},{"name":"Трудова","type":"вул.","houses":[[1,2,3,4,5,6,7,8,9,10,11,12,13,14,15,16,17,18,19,20,21,22,23,24,25,26,27,28,29,30,31,32,33,34,35,36,37,38,39,40,41,42]]},{"name":"Шевченка","type":"вул.","houses":[[1,2,3,4,5,6,7]]}]