[{"name":"Боженка","type":"вул.","houses":[[1,2,3,4,5,6,7,8,9,10,11,12,13,14,15,"15А",16,17,18,19,20,22,24,41,79,"79А",80,"80А",101,111,112,114]]},{"name":"Вишнева","type":"вул.","houses":[[1,2,3,4,5,6,7,8,9,10,11,12,13,14,15,16,17,18,19,20,21,22,23,24,25,26,28,30,31,32,34,36,38,40]]},{"name":"Героїв Чорнобиля","type":"вул.","houses":[[1,2,3,4,5,6,7,8,9,10,13,14,"14А",15,16,17,18,19,20,21,22,27,28,29,30,31,32,33,34,35,36,37,38,40,134]]},{"name":"Квітнева","type":"вул.","houses":[[24,36,96]]},{"name":"Клименка","type":"вул.","houses":[[1,6,9,43,138]]},{"name":"Матросова","type":"вул.","houses":[[3,4,5,6,7,"7А",8,10,12]]},{"name":"Піонерська","type":"вул.","houses":[[1,2,3,4,5,6,7,8,9,10,11,12,13,14,15,16,17,"17А","17Б",19,"21А",23,"23А"]]},{"name":"Ставкова","type":"вул.","houses":[["1А","2А",3,116]]},{"name":"Фабрична","type":"вул.","houses":[[1,69]]},{"name":"Боженка","type":"пров.","houses":[[1,2,3,4,5,6,7,8,9,10,12,14,29,"29А",31,33,37,41]]},{"name":"Зелений","type":"пров.","houses":[[1,2,3,4,"4А",5,7,"7А"]]},{"name":"Піонерський","type":"пров.","houses":[[2,"2А",4]]}]