[{"name":"1 травня","type":"вул.","houses":[[1,4,9,10,12,3,4,5,13,16,17,18,23,25,54]]},{"name":"17 вересня","type":"вул.","houses":[[1,11,25,35,39,40,41,42,43,44,46,47,49,53,56]]},{"name":"Богдана Хмельницького","type":"вул.","houses":[[2,5,6,9,10,12,13,17,21,22,24,28,30,31,32],[13]]},{"name":"Гагаріна","type":"вул.","houses":[[3,4,10,12,16,18,19,21,25,27,29,34,35,37]]},{"name":"Загородня","type":"вул.","houses":[[1,2,3,4,5,7,8,9,10,11,12,14,16,17,19,21,22,23,25]]},{"name":"Кобилянської","type":"вул.","houses":[[50,55,56,58,59,60]]},{"name":"Конституції","type":"вул.","houses":[[65,65,68,69,70,71,72,74,75,80]]},{"name":"Космонавтів","type":"вул.","houses":[[24],[81,83,84,103,104,105,106,107,118,119,126]]},{"name":"Лесі Українки","type":"вул.","houses":[[1,2,3,4,5,12],[25]]},{"name":"Миру","type":"вул.","houses":[[24,25,26,27,28],[3,4,7],[1,2,10]]},{"name":"Незалежності","type":"вул.","houses":[[1,5,7,14,15,16,17,21,22,24,25,26,27,28,29],[86,88,89,95,97,100],[2,3,5,6,8,10,11,12,13,14,15,16]]},{"name":"Нова","type":"вул.","houses":[[1]]},{"name":"Підкума","type":"вул.","houses":[[3,4,6,7,10,13,14,15,20]]},{"name":"Польова","type":"вул.","houses":[[1,2,3,4,5,6,7],[12]]},{"name":"Пушкіна","type":"вул.","houses":[[25],[3],[2,8,9,10,11,12,14,15,16,18,20,21,23,25,27,29,30,31,33,37,41,42,45,46,47,48,50,57,58,62,37,50,52,58,59,60,68,69,72,73,77,82]]},{"name":"Січових Стрільців","type":"вул.","houses":[[2,4,6,10,13,14,20,22,25,26,28,31,33,69]]},{"name":"Стефаника","type":"вул.","houses":[[1,9],[1,2,3,5,7,8,14,16,17,18,20,21,26,27,56,28]]},{"name":"Українська","type":"вул.","houses":[[1,2]]},{"name":"Франка","type":"вул.","houses":[[1,2,3,4,5,6,7,8,9,10,11,23],[3,10,11,12]]},{"name":"Черемшини","type":"вул.","houses":[[2,6,8,24]]},{"name":"Чехова","type":"вул.","houses":[[25],[2,26,30,43]]},{"name":"Шевченка","type":"вул.","houses":[[1,2,3,4,5,6,7,8,12,13,14,15,16,20,23,24,25,28,31,35,34,37,38,39,40,41,43,44,48,53,71,81],[3]]}]