[{"name":"1 травня","type":"вул.","houses":[[1,3,4,5,7,9,10,11,13,15,17,18,19,21]]},{"name":"60р Жовтня","type":"вул.","houses":[[1,2,3,4,5,6,7,8,10,11,12,13,14,15]]},{"name":"Б.Хмельницького","type":"вул.","houses":[[1,2,3,4,5,6,7,8,9,10,11,12,13,14,15,16,17,18,19,20,21,22,23,24,25]]},{"name":"Буковинська","type":"вул.","houses":[[1,2,3,4,5,6,7,8,10,11,12,13,14,15,16,17,18,19,20,21,22,23,24,25,26,27,28,30,31],[1,2,3,4,5,6,7,8,9,10,11,12,13,14,15,16,17,18,19,20,21,22,23,24,25,26,27,28,29,30,30,31,32,33,34,35,36,37,38,39,40,41,42,43,44,45]]},{"name":"В.Вівчука","type":"вул.","houses":[[1,2,3,4,5,6,7,8,9,10]]},{"name":"В.Стуса","type":"вул.","houses":[[1,2,3,4,5,6,7,8,9,10]]},{"name":"В.Шкрібляка","type":"вул.","houses":[[1,2,3,4,5,6,7,8,9,10,11,12,13,14,15,16,17,18,19,20]]},{"name":"Весняна","type":"вул.","houses":[[1,2,3,4,5,6,7,8,10,11,12,13,14,15,16,17,18,19,20]]},{"name":"Вокзальна","type":"вул.","houses":[[1,2,3,4,5,6,7,8,10,11,12,13,14,15,16,17,18,19]]},{"name":"Головна","type":"вул.","houses":[[1,2,3,4,5,6,7,8,9,10,11,12,13,14,15,16,17,18,19,20,21,22,23,24,25,26,27,28,29,30,31,32]]},{"name":"Горького","type":"вул.","houses":[[1,2,3,4,5,6,7,8,10,11,12,13,14,15,16]]},{"name":"Дружби","type":"вул.","houses":[[1,2,3,4,5,6,7,8,9]]},{"name":"Є.Гребінки","type":"вул.","houses":[[1,2,3,4,5,6,7,8,10,12,13,14,15,16,17,18,19,20,21,22,23,24,25,26,27]]},{"name":"Жовтнева","type":"вул.","houses":[[1,2,3,4,5,6,7,8,10,11,12,13,14,15,16,17,18,19,20,21,22,23,24,25,26,27,28,30,31]]},{"name":"Жукова","type":"вул.","houses":[[1,2,3,4,5,6,7,8,10,11,12,13,14,15,16,17,18,19,20]]},{"name":"І.Дощівника","type":"вул.","houses":[[1,2,3,4,5,6,7,8,9,10,11,12,13,14,16,18,20,22,24,26]]},{"name":"І.Миколайчука","type":"вул.","houses":[[1,2,3,4,5,6,7,8,10,11]]},{"name":"І.Франка","type":"вул.","houses":[[1,2,3,4,5,6,7,8,9,10,11,13,14,15]]},{"name":"Лесі Українки","type":"вул.","houses":[[1,2,3,4,5,6,7,8,10]]},{"name":"Лізи Чайкіної","type":"вул.","houses":[[1,2,3,4,5,6,7,8,9,10,11,12,13,14,15,16,17,18,19,20,21,22,23,24,25,26,27]]},{"name":"М.Гаврилюка","type":"вул.","houses":[[1,2,3,4,5,6,7,8,10,11,12]]},{"name":"М.Іванчука","type":"вул.","houses":[[1,2,3,4,5,6,7]]},{"name":"М.Коцюбинського","type":"вул.","houses":[[1,2,3,4,5,6,7,8,9]]},{"name":"М.Лисенка","type":"вул.","houses":[[1,2,3,4,5,6,7,8,10,11,12,13,14,15],[1,2,3,4,5,6,7,8,9,10,11,12,13,14,15,16,17,18,19,20,21,22,23,24,25,26,27,28,29,30,31]]},{"name":"Молодіжна","type":"вул.","houses":[[1,2,3,4,5,6,7,8,9,10,11,12,13,14,15,16,17,18,19,20,21,22,23,24,25,26,27,28]]},{"name":"Незалежності","type":"вул.","houses":[[1,2,3,4,5,6,7,8,10,11]]},{"name":"Нечуя-Левицького","type":"вул.","houses":[[1,2,3,4,5,6,7,8,9,10,11,12,13,14,15,16,17,18,19]]},{"name":"О.Вишні","type":"вул.","houses":[[1,2,3,4,5,6,7,8,10,11,12,13,14,15,16]]},{"name":"О.Довбуша","type":"вул.","houses":[[1,2,3,4,5,6,7,8,9,10,11]]},{"name":"О.Кобилянської","type":"вул.","houses":[[1,2,3,4,5,6,7,8,9,10,11,12,13,14,15,16,17,18,19,20,21,22,23,24,25,26,27,28,29,30,30,31,32,33,34,35,36,37,38,39,40,41,42,43,44,45]]},{"name":"П.Тичини","type":"вул.","houses":[[1,2,3,4,5,6,7,8,9,10,11,12,13,14,15,16,17,18,19,20,21,22,23,24,25,26,27,28,29]]},{"name":"Підбережна","type":"вул.","houses":[[1,2,3,4,5,6,7,8,10,11,12,13,14,15,16]]},{"name":"Підгірна","type":"вул.","houses":[[1,2,3,4,5,6]]},{"name":"Підзабережна","type":"вул.","houses":[[1]]},{"name":"Романенка","type":"вул.","houses":[[19,20,21,22,23,24,25,26,27,28,29,30,31,32,33,34,35,36,37,38,39,40,41,42],[1,2,3,4,5,6,7,8,10,11,12,13,14,15,16,17,18]]},{"name":"С.Воробкевича","type":"вул.","houses":[[1,2,3,4,5,6,7,8,9,10,11,12,13,15,17,19]]},{"name":"С.Ковпака","type":"вул.","houses":[[1,2,3,4,5,6,7,8,10,11,12,13,14,15,16]]},{"name":"Січових Стрільців","type":"вул.","houses":[[1,2,3,4,5,6,7,8,9,10]]},{"name":"Т.Шевченка","type":"вул.","houses":[[1,2,"2А",3,4,5,6,7,8,10,11,12,13,14,15,16,17,18,19]]},{"name":"Типова","type":"вул.","houses":[[1,2,3,4,5,6,7,8,10,11,12,13,14]]},{"name":"У.Кармелюка","type":"вул.","houses":[[1,2,3,4,5,6,7,8,10,11,12,13,14,15,16,17,18],[1,2,3,4,5,6,7,8,13,14,15,16,17,18,19,20,21,22,23,24,25,26,27,28,29]]},{"name":"Українська","type":"вул.","houses":[[1,2,3,4,5,6,7,8,9,10,11,12,13,14,15,16,17,18]]},{"name":"Чернівецька","type":"вул.","houses":[[1,2,3,4,5,6,7,8,10,11,12,13,14,15,16]]},{"name":"Ю.Гагаріна","type":"вул.","houses":[[1,2,3,4,5,6,7,8,13,14,15,16,17,18,19,20,21,22,23,24,25,26,27,28,29,30]]},{"name":"Ю.Федьковича","type":"вул.","houses":[[12,3,4,5,6,7,8,9,10,11,12,13,14,15,16,17,18,19,20,21,22,23,24,25]]}]